README.txt
setup.cfg
setup.py
Products/__init__.py
Products.ClockServer.egg-info/PKG-INFO
Products.ClockServer.egg-info/SOURCES.txt
Products.ClockServer.egg-info/dependency_links.txt
Products.ClockServer.egg-info/entry_points.txt
Products.ClockServer.egg-info/namespace_packages.txt
Products.ClockServer.egg-info/not-zip-safe
Products.ClockServer.egg-info/paster_plugins.txt
Products.ClockServer.egg-info/requires.txt
Products.ClockServer.egg-info/top_level.txt
Products/ClockServer/ClockServer.py
Products/ClockServer/__init__.py
Products/ClockServer/component.xml
Products/ClockServer/configure.zcml
Products/ClockServer/datatypes.py
Products/ClockServer/tests.py
