Metadata-Version: 1.0
Name: Products.ClockServer
Version: 0.2-Zope2.9dev
Summary: The Zope ClockServer product provides a mechanism for users to call Zope object methods without the use of an external clock source (e.g. cron/wget).
Home-page: http://labs.menttes.com/zope/products/clockserver
Author: Roberto Allende
Author-email: rover@menttes.com
License: ZPL 2.1
Platform: UNKNOWN
Classifier: Framework :: Plone
Classifier: Framework :: Zope2
Classifier: Framework :: Zope3
Classifier: Programming Language :: Python
Classifier: Topic :: Software Development :: Libraries :: Python Modules
